sheol/__init__.py
sheol/cli.py
sheol/sheol.py
sheol-0.0.1.dist-info/METADATA
sheol-0.0.1.dist-info/RECORD
sheol-0.0.1.dist-info/WHEEL
sheol-0.0.1.dist-info/entry_points.txt
sheol-0.0.1.dist-info/top_level.txt
