Metadata-Version: 2.1
Name: sheol
Version: 0.0.1
Summary: Tools for maintaining pandomics process files.
Home-page: https://github.com/draperjames/sheol
Author: James Draper
Author-email: james.draper@proton.mail.com
License: BSD license
Keywords: sheol
Platform: UNKNOWN
Classifier: Development Status :: 2 - Pre-Alpha
Classifier: Intended Audience :: Developers
Classifier: License :: OSI Approved :: BSD License
Classifier: Natural Language :: English
Classifier: Programming Language :: Python :: 2
Classifier: Programming Language :: Python :: 2.7
Classifier: Programming Language :: Python :: 3
Classifier: Programming Language :: Python :: 3.4
Classifier: Programming Language :: Python :: 3.5
Classifier: Programming Language :: Python :: 3.6
Requires-Dist: Click (>=6.0)
